LICENSE
README.md
pyproject.toml
src/touhoubbbunits/__init__.py
src/touhoubbbunits/randomizer.py
src/touhoubbbunits.egg-info/PKG-INFO
src/touhoubbbunits.egg-info/SOURCES.txt
src/touhoubbbunits.egg-info/dependency_links.txt
src/touhoubbbunits.egg-info/requires.txt
src/touhoubbbunits.egg-info/top_level.txt