Metadata-Version: 2.4
Name: touhoubbbunits
Version: 0.2.1
Summary: 用于直接导入东方同人作品东方大战争的兵种信息,附带一个全随机器
Author-email: Komeiji_HSS <1271349487@qq.com>
Classifier: Programming Language :: Python :: 3.11
Classifier: License :: OSI Approved :: MIT License
Requires-Python: >=3.9
License-File: LICENSE
Requires-Dist: random
Requires-Dist: tkinter
Dynamic: license-file
